pureyaml/__init__.py
pureyaml/_compat.py
pureyaml/decoder.py
pureyaml/encoder.py
pureyaml/exceptions.py
pureyaml/nodes.py
pureyaml/parser.py
pureyaml/utils.py
pureyaml/grammar/__init__.py
pureyaml/grammar/_parsetab.py
pureyaml/grammar/productions.py
pureyaml/grammar/tokens.py
pureyaml/grammar/utils.py
pureyaml-0.1.0.dist-info/DESCRIPTION.rst
pureyaml-0.1.0.dist-info/METADATA
pureyaml-0.1.0.dist-info/RECORD
pureyaml-0.1.0.dist-info/WHEEL
pureyaml-0.1.0.dist-info/metadata.json
pureyaml-0.1.0.dist-info/top_level.txt
